aravis/__init__.py
aravis/version.py
aravis/lib/Aravis-0.8.typelib
aravis/lib/README.md
aravis/lib/libaravis-0.8.so
aravis/lib/libaravis-0.8.so.0
aravis/lib/libaravis-0.8.so.0.8.31
aravis_python-0.8.31.post1.dist-info/COPYING.txt
aravis_python-0.8.31.post1.dist-info/METADATA
aravis_python-0.8.31.post1.dist-info/WHEEL
aravis_python-0.8.31.post1.dist-info/top_level.txt
aravis_python-0.8.31.post1.dist-info/RECORD
