Metadata-Version: 2.1
Name: aravis-python
Version: 0.8.31.post1
Summary: Python Binding for aravis
License: GNU General Public License
Classifier: Development Status :: 3 - Alpha
Classifier: Programming Language :: Python :: 3
Classifier: Programming Language :: Python :: 3 :: Only
Classifier: Programming Language :: Python :: 3.9
Classifier: Programming Language :: Python :: 3.10
Classifier: Programming Language :: Python :: 3.11
Classifier: Programming Language :: Python :: 3.12
Requires-Python: >=3.9.0
License-File: COPYING.txt
